kantrack/__init__.py
kantrack/cli.py
kantrack/server.py
kantrack/static/index.html
kantrack/utils.py
kantrack-0.1.7.dist-info/LICENSE
kantrack-0.1.7.dist-info/METADATA
kantrack-0.1.7.dist-info/WHEEL
kantrack-0.1.7.dist-info/entry_points.txt
kantrack-0.1.7.dist-info/RECORD
