Metadata-Version: 2.1
Name: kantrack
Version: 0.1.7
Summary: Super lightweight task tracker that integrates directly with Git repositories.
Home-page: https://github.com/EdCo95/kantrack
License: MIT
Author: Ed Collins
Author-email: edward.g.collins.1995@gmail.com
Requires-Python: >=3.9,<4.0
Classifier: License :: OSI Approved :: MIT License
Classifier: Programming Language :: Python :: 3
Classifier: Programming Language :: Python :: 3.9
Classifier: Programming Language :: Python :: 3.10
Classifier: Programming Language :: Python :: 3.11
Classifier: Programming Language :: Python :: 3.12
Requires-Dist: fastapi (>=0.115.8,<0.116.0)
Requires-Dist: requests (>=2.32.3,<3.0.0)
Requires-Dist: typer (>=0.15.1,<0.16.0)
Requires-Dist: uvicorn (>=0.34.0,<0.35.0)
Project-URL: Repository, https://github.com/EdCo95/kantrack
